fixtureless/__init__.py
fixtureless/constants.py
fixtureless/exceptions.py
fixtureless/factory.py
fixtureless/generator.py
fixtureless/utils.py
neutron_fixtureless-1.4.3.5.dist-info/LICENSE.txt
neutron_fixtureless-1.4.3.5.dist-info/METADATA
neutron_fixtureless-1.4.3.5.dist-info/WHEEL
neutron_fixtureless-1.4.3.5.dist-info/top_level.txt
neutron_fixtureless-1.4.3.5.dist-info/RECORD
